CHANGES.txt
COPYRIGHT.txt
INSTALL.txt
KNOWNBUGS.txt
LICENSE.txt
README.txt
TODO.txt
base.cfg
bootstrap.py
buildout.cfg.example
setup.py
versions.cfg
doc/BLOBS.txt
doc/CMDLINE.txt
doc/DEPLOYMENT.txt
doc/OPERATION.txt
src/gocept/__init__.py
src/gocept.zeoraid.egg-info/PKG-INFO
src/gocept.zeoraid.egg-info/SOURCES.txt
src/gocept.zeoraid.egg-info/dependency_links.txt
src/gocept.zeoraid.egg-info/entry_points.txt
src/gocept.zeoraid.egg-info/namespace_packages.txt
src/gocept.zeoraid.egg-info/not-zip-safe
src/gocept.zeoraid.egg-info/requires.txt
src/gocept.zeoraid.egg-info/top_level.txt
src/gocept/zeoraid/__init__.py
src/gocept/zeoraid/component.xml
src/gocept/zeoraid/datatypes.py
src/gocept/zeoraid/filestorage.py
src/gocept/zeoraid/interfaces.py
src/gocept/zeoraid/recovery.py
src/gocept/zeoraid/storage.py
src/gocept/zeoraid/testing.py
src/gocept/zeoraid/utils.py
src/gocept/zeoraid/scripts/__init__.py
src/gocept/zeoraid/scripts/controller.py
src/gocept/zeoraid/scripts/recipe.py
src/gocept/zeoraid/scripts/recipe.txt
src/gocept/zeoraid/scripts/stresstest.py
src/gocept/zeoraid/scripts/tests.py
src/gocept/zeoraid/tests/__init__.py
src/gocept/zeoraid/tests/component.xml
src/gocept/zeoraid/tests/failingstorage.py
src/gocept/zeoraid/tests/loggingstorage.py
src/gocept/zeoraid/tests/test_basics.py
src/gocept/zeoraid/tests/test_recovery.py
src/gocept/zeoraid/tests/test_zeo.py