Metadata-Version: 1.0
Name: gocept.zeoraid
Version: 1.0b8
Summary: A ZODB storage for replication using RAID techniques.
Home-page: http://pypi.python.org/pypi/gocept.zeoraid
Author: Zope Foundation and Contributors
Author-email: ct@gocept.com
License: ZPL 2.1
Keywords: zodb buildout
Platform: UNKNOWN
Classifier: Framework :: Buildout
